bio_compose/__init__.py
bio_compose/__main__.py
bio_compose/api.py
bio_compose/bundles.py
bio_compose/composer.py
bio_compose/data_model.py
bio_compose/processing_tools.py
bio_compose/runner.py
bio_compose/verifier.py
pyproject.toml
tests/__init__.py
tests/fixtures/BIOMD0000000013.omex
tests/fixtures/BIOMD0000000019.omex
tests/fixtures/BIOMD0000000044.omex
tests/fixtures/sbml-core/BIOMD0000000001.omex
tests/fixtures/sbml-core/BIOMD0000000001_url.xml
tests/fixtures/sbml-core/BIOMD0000000001_url.xml.psc
tests/fixtures/sbml-core/BIOMD0000000005.omex
tests/fixtures/sbml-core/BIOMD0000000005_url.xml
tests/fixtures/sbml-core/BIOMD0000000010_url.xml
tests/fixtures/sbml-core/BIOMD0000000488_url.xml
tests/fixtures/sbml-core/Caravagna-J-Theor-Biol-2010-tumor-suppressive-oscillations/BIOMD0000000912_sim.sedml
tests/fixtures/sbml-core/Caravagna-J-Theor-Biol-2010-tumor-suppressive-oscillations/Caravagna2010.xml
tests/fixtures/sbml-core/Caravagna-J-Theor-Biol-2010-tumor-suppressive-oscillations/Figure1.jpg
tests/fixtures/sbml-core/Caravagna-J-Theor-Biol-2010-tumor-suppressive-oscillations/expected-results.json
tests/fixtures/sbml-core/Caravagna-J-Theor-Biol-2010-tumor-suppressive-oscillations/manifest.xml
tests/fixtures/sbml-core/Caravagna-J-Theor-Biol-2010-tumor-suppressive-oscillations/metadata.rdf
tests/fixtures/sbml-core/Caravagna-J-Theor-Biol-2010-tumor-suppressive-oscillations/reports.h5
tests/fixtures/sbml-core/Caravagna-J-Theor-Biol-2010-tumor-suppressive-oscillations.omex
tests/fixtures/sbml-core/Ciliberto-J-Cell-Biol-2003-morphogenesis-checkpoint-Fehlberg/BIOMD0000000297_url.xml
tests/fixtures/sbml-core/Ciliberto-J-Cell-Biol-2003-morphogenesis-checkpoint-Fehlberg/Figure1.jpg
tests/fixtures/sbml-core/Ciliberto-J-Cell-Biol-2003-morphogenesis-checkpoint-Fehlberg/Figure2.jpg
tests/fixtures/sbml-core/Ciliberto-J-Cell-Biol-2003-morphogenesis-checkpoint-Fehlberg/Figure3.vg.json
bio_compose-0.8.7.dist-info/LICENSE
bio_compose-0.8.7.dist-info/METADATA
bio_compose-0.8.7.dist-info/WHEEL
bio_compose-0.8.7.dist-info/entry_points.txt
bio_compose-0.8.7.dist-info/RECORD
