Metadata-Version: 2.1
Name: bio-compose
Version: 0.8.7
Summary: Create, execute, and introspect reproducible composite simulations of dynamic biological systems.
Author: Alex Patrie
Author-email: alexanderpatrie@gmail.com
Requires-Python: >=3.10,<4.0
Classifier: Programming Language :: Python :: 3
Classifier: Programming Language :: Python :: 3.10
Classifier: Programming Language :: Python :: 3.11
Classifier: Programming Language :: Python :: 3.12
Classifier: Programming Language :: Python :: 3.13
Requires-Dist: antimony
Requires-Dist: process-bigraph (>=0.0.21,<0.0.22)
Requires-Dist: requests (>=2.32.3,<3.0.0)
Requires-Dist: requests-toolbelt (>=1.0.0,<2.0.0)
Requires-Dist: seaborn (>=0.13.2,<0.14.0)
Requires-Dist: toml (>=0.10.2,<0.11.0)
